structurealign/__init__.py
structurealign/aligner.py
structurealign/models.py
structurealign-0.1.0.dist-info/LICENSE
structurealign-0.1.0.dist-info/METADATA
structurealign-0.1.0.dist-info/WHEEL
structurealign-0.1.0.dist-info/RECORD
