Metadata-Version: 2.3
Name: structurealign
Version: 0.1.0
Summary: Tool to align protein structures with differing lengths
License: MIT
Author: haeussma
Author-email: 83341109+haeussma@users.noreply.github.com
Requires-Python: >=3.10,<4.0
Classifier: License :: OSI Approved :: MIT License
Classifier: Programming Language :: Python :: 3
Classifier: Programming Language :: Python :: 3.10
Classifier: Programming Language :: Python :: 3.11
Classifier: Programming Language :: Python :: 3.12
Classifier: Programming Language :: Python :: 3.13
Requires-Dist: biopython (>=1.83,<2.0)
Requires-Dist: matplotlib (>=3.7.0,<4.0.0)
Requires-Dist: mdanalysis (>=2.0.0,<3.0.0)
Requires-Dist: numpy (>=1.24.0,<2.0.0)
Requires-Dist: pandas (>=2.0.0,<3.0.0)
Requires-Dist: plotly (>=5.17.0,<6.0.0)
Requires-Dist: pydantic (>=2.5.0,<3.0.0)
